Metadata-Version: 2.4
Name: xlsx-to-sdif
Version: 0.1.6
Summary: Convert XLSX files to SDIF files.
Author: Syncpulse
Maintainer-email: Bryan Djafer <bryan.djafer@syncpulse.fr>
License-Expression: MIT
Requires-Python: <3.14,>=3.10
License-File: LICENSE
Dynamic: license-file
